basiclive/__init__.py
basiclive/version.py
basiclive/accounts/__init__.py
basiclive/accounts/cas/__init__.py
basiclive/accounts/cas/apps.py
basiclive/accounts/cas/models.py
basiclive/accounts/ldap/__init__.py
basiclive/accounts/ldap/apps.py
basiclive/accounts/ldap/models.py
basiclive/accounts/ldap/slap.py
basiclive/auth/__init__.py
basiclive/auth/cas/__init__.py
basiclive/auth/cas/apps.py
basiclive/auth/cas/settings-cas.py
basiclive/auth/cas/urls.py
basiclive/auth/ldap/__init__.py
basiclive/auth/ldap/apps.py
basiclive/auth/ldap/settings-ldap.py
basiclive/auth/ldap/urls.py
basiclive/core/__init__.py
basiclive/core/acl/__init__.py
basiclive/core/acl/admin.py
basiclive/core/acl/apps.py
basiclive/core/acl/forms.py
basiclive/core/acl/models.py
basiclive/core/acl/tests.py
basiclive/core/acl/urls.py
basiclive/core/acl/views.py
basiclive/core/acl/migrations/0001_initial.py
basiclive/core/acl/migrations/0002_usercategory.py
basiclive/core/acl/migrations/0003_remoteconnection.py
basiclive/core/acl/migrations/0004_auto_20180619_1530.py
basiclive/core/acl/migrations/0005_auto_20190409_1457.py
basiclive/core/acl/migrations/0006_auto_20190907_2214.py
basiclive/core/acl/migrations/0007_announcement_staff_only.py
basiclive/core/acl/migrations/0008_auto_20191219_1940.py
basiclive/core/acl/migrations/0009_auto_20191229_2336.py
basiclive/core/acl/migrations/0010_announcement_modal.py
basiclive/core/acl/migrations/0011_delete_announcement.py
basiclive/core/acl/migrations/0012_delete_usercategory.py
basiclive/core/acl/migrations/0013_userlist_beamline.py
basiclive/core/acl/migrations/0014_auto_20200715_0955.py
basiclive/core/acl/migrations/0015_auto_20200923_0857.py
basiclive/core/acl/migrations/0016_auto_20201202_1327.py
basiclive/core/acl/migrations/0017_auto_20201202_1627.py
basiclive/core/acl/migrations/0018_auto_20201202_1629.py
basiclive/core/acl/migrations/0019_auto_20201202_1632.py
basiclive/core/acl/migrations/__init__.py
basiclive/core/acl/templates/acl/tools-access.html
basiclive-0.1.0.36.dist-info/LICENSE
basiclive-0.1.0.36.dist-info/METADATA
basiclive-0.1.0.36.dist-info/WHEEL
basiclive-0.1.0.36.dist-info/top_level.txt
basiclive-0.1.0.36.dist-info/RECORD
